harrixpyssg/__init__.py
harrixpyssg/article.py
harrixpyssg/dir_md_to_dir_html.py
harrixpyssg/markdown_to_html.py
harrixpyssg/static_site_generator.py
harrix_pyssg-0.5.dist-info/LICENSE
harrix_pyssg-0.5.dist-info/METADATA
harrix_pyssg-0.5.dist-info/WHEEL
harrix_pyssg-0.5.dist-info/top_level.txt
harrix_pyssg-0.5.dist-info/RECORD
