Metadata-Version: 2.1
Name: harrix-pyssg
Version: 0.5
Summary: Static site generator
Home-page: https://github.com/Harrix/harrix-pylib
Author: Anton Sergienko
Author-email: anton.b.sergienko@gmail.com
License: UNKNOWN
Platform: UNKNOWN
License-File: LICENSE
Requires-Dist: markdown
Requires-Dist: harrix-pylib
